README.md
setup.cfg
setup.py
waterfall.py
waterfallcharts.egg-info/PKG-INFO
waterfallcharts.egg-info/SOURCES.txt
waterfallcharts.egg-info/dependency_links.txt
waterfallcharts.egg-info/top_level.txt