Metadata-Version: 1.1
Name: waterfallcharts
Version: 3.3
Summary: Quickly generates standard waterfall charts, takes two ordered lists as inputs.
Home-page: https://github.com/chrispaulca/waterfall
Author: Christopher Paul Csiszar
Author-email: christopher.csiszar@gmail.com
License: UNKNOWN
Download-URL: https://github.com/chrispaulca/waterfall/archive/v3.3.tar.gz
Keywords: waterfall,chart,charts,accounting,automate,random forest,decision tree
Platform: UNKNOWN
